{
  "fetchedAt": "2026-07-12T02:46:56Z",
  "href": "https://www.boltonvalley.com/winter/trail-maps-snow-reports/snow-reports/",
  "id": "bolton-valley",
  "lifts": {
    "stats": {
      "closed": 0,
      "hold": 0,
      "open": 0,
      "percentage": {
        "closed": 25,
        "hold": 25,
        "open": 25,
        "scheduled": 25
      },
      "scheduled": 0
    },
    "status": {}
  },
  "ll": [
    -72.84948,
    44.421673
  ],
  "name": "Bolton Valley",
  "timestamp": {
    "lifts": 1783824202421,
    "opening": 1783824201840,
    "weather": 0,
    "webcams": 0
  }
}
