{
  "fetchedAt": "2026-07-22T19:30:33Z",
  "href": "https://www.donnerskiranch.com/liftstatus",
  "id": "donner-ski-ranch",
  "lifts": {
    "stats": {
      "closed": 0,
      "hold": 0,
      "open": 0,
      "percentage": {
        "closed": 25,
        "hold": 25,
        "open": 25,
        "scheduled": 25
      },
      "scheduled": 0
    },
    "status": {}
  },
  "ll": [
    -120.330422,
    39.317661
  ],
  "name": "Donner Ski Ranch",
  "timestamp": {
    "lifts": 1784747762752,
    "opening": 1784737544080,
    "trails": 1784747761286,
    "weather": 0,
    "webcams": 0
  }
}
